ggufloader/__init__.py
ggufloader/addon_manager.py
ggufloader/config.py
ggufloader/gguf_loader_main.py
ggufloader/icon.ico
ggufloader/main.py
ggufloader/resource_manager.py
ggufloader/utils.py
ggufloader/addons/__init__.py
ggufloader/addons/smart_floater/INTEGRATION_SUMMARY.md
ggufloader/addons/smart_floater/PERFORMANCE_OPTIMIZATION.md
ggufloader/addons/smart_floater/__init__.py
ggufloader/addons/smart_floater/comment_engine.py
ggufloader/addons/smart_floater/data_models.py
ggufloader/addons/smart_floater/error_handler.py
ggufloader/addons/smart_floater/floater_ui.py
ggufloader/addons/smart_floater/injector.py
ggufloader/addons/smart_floater/integration.py
ggufloader/addons/smart_floater/main.py
ggufloader/addons/smart_floater/performance_optimizer.py
ggufloader/addons/smart_floater/privacy_security.py
ggufloader/addons/smart_floater/simple_main.py
ggufloader/addons/smart_floater/.pytest_cache/README.md
ggufloader/docs/README.md
ggufloader/docs/addon-api.md
ggufloader/docs/addon-development.md
ggufloader/docs/installation.md
ggufloader/docs/package-structure.md
ggufloader/docs/quick-start.md
ggufloader/docs/smart-floater-example.md
ggufloader/mixins/__init__.py
ggufloader/mixins/addon_mixin.py
ggufloader/mixins/chat_handler_mixin.py
ggufloader/mixins/event_handler_mixin.py
ggufloader/mixins/model_handler_mixin.py
ggufloader/mixins/ui_setup_mixin.py
ggufloader/mixins/utils_mixin.py
ggufloader/models/__init__.py
ggufloader/models/addon_manager.py
ggufloader/models/chat_generator.py
ggufloader/models/model_loader.py
ggufloader/ui/__init__.py
ggufloader/ui/ai_chat_window.py
ggufloader/ui/apply_style.py
ggufloader/widgets/__init__.py
ggufloader/widgets/addon_sidebar.py
ggufloader/widgets/chat_bubble.py
ggufloader/widgets/collapsible_widget.py
ggufloader-2.0.1.dist-info/licenses/LICENSE
ggufloader-2.0.1.dist-info/METADATA
ggufloader-2.0.1.dist-info/WHEEL
ggufloader-2.0.1.dist-info/entry_points.txt
ggufloader-2.0.1.dist-info/top_level.txt
ggufloader-2.0.1.dist-info/RECORD
