Metadata-Version: 2.4
Name: ggufloader
Version: 2.0.1
Summary: Advanced GGUF Model Loader with Smart Floating Assistant
Author-email: Hussain Nazary <hussainnazary475@gmail.com>
Maintainer-email: Hussain Nazary <hussainnazary475@gmail.com>
License-Expression: MIT
Project-URL: Homepage, https://ggufloader.github.io
Project-URL: Repository, https://github.com/GGUFloader/gguf-loader
Project-URL: Documentation, https://ggufloader.github.io
Project-URL: Bug Tracker, https://github.com/GGUFloader/gguf-loader/issues
Keywords: gguf,llama,ai,model-loader,gui,pyside6
Classifier: Development Status :: 4 - Beta
Classifier: Intended Audience :: Developers
Classifier: Intended Audience :: End Users/Desktop
Classifier: Operating System :: Microsoft :: Windows :: Windows 10
Classifier: Operating System :: Microsoft :: Windows :: Windows 11
Classifier: Operating System :: MacOS :: MacOS X
Classifier: Operating System :: POSIX :: Linux
Classifier: Programming Language :: Python :: 3
Classifier: Programming Language :: Python :: 3.8
Classifier: Programming Language :: Python :: 3.9
Classifier: Programming Language :: Python :: 3.10
Classifier: Programming Language :: Python :: 3.11
Classifier: Programming Language :: Python :: 3.12
Classifier: Topic :: Scientific/Engineering :: Artificial Intelligence
Classifier: Topic :: Software Development :: Libraries :: Python Modules
Classifier: Environment :: X11 Applications :: Qt
Classifier: Environment :: Win32 (MS Windows)
Classifier: Environment :: MacOS X
Requires-Python: >=3.8
License-File: LICENSE
Requires-Dist: PySide6>=6.0.0
Requires-Dist: llama-cpp-python>=0.2.0
Requires-Dist: pyautogui>=0.9.50
Requires-Dist: pyperclip>=1.8.0
Requires-Dist: pywin32>=227; sys_platform == "win32"
Provides-Extra: dev
Requires-Dist: build; extra == "dev"
Requires-Dist: twine; extra == "dev"
Requires-Dist: pytest; extra == "dev"
Requires-Dist: black; extra == "dev"
Requires-Dist: flake8; extra == "dev"
Provides-Extra: performance
Requires-Dist: psutil>=5.8.0; extra == "performance"
Provides-Extra: windows
Requires-Dist: pywin32>=227; extra == "windows"
Provides-Extra: linux
Requires-Dist: python-xlib>=0.29; sys_platform == "linux" and extra == "linux"
Provides-Extra: macos
Requires-Dist: pyobjc-framework-Cocoa>=8.0; sys_platform == "darwin" and extra == "macos"
Requires-Dist: pyobjc-framework-Quartz>=8.0; sys_platform == "darwin" and extra == "macos"
Provides-Extra: all
Requires-Dist: psutil>=5.8.0; extra == "all"
Requires-Dist: pywin32>=227; sys_platform == "win32" and extra == "all"
Requires-Dist: python-xlib>=0.29; sys_platform == "linux" and extra == "all"
Requires-Dist: pyobjc-framework-Cocoa>=8.0; sys_platform == "darwin" and extra == "all"
Requires-Dist: pyobjc-framework-Quartz>=8.0; sys_platform == "darwin" and extra == "all"
Dynamic: license-file
